envtools/__init__.py
envtools/databases.py
envtools/environment.py
envtools/logging_config.py
envtools/django/__init__.py
envtools/django/database.py
python_envtools-0.0.1.dev1.dist-info/DESCRIPTION.rst
python_envtools-0.0.1.dev1.dist-info/METADATA
python_envtools-0.0.1.dev1.dist-info/RECORD
python_envtools-0.0.1.dev1.dist-info/WHEEL
python_envtools-0.0.1.dev1.dist-info/metadata.json
python_envtools-0.0.1.dev1.dist-info/pbr.json
python_envtools-0.0.1.dev1.dist-info/top_level.txt
