Metadata-Version: 2.0
Name: python-envtools
Version: 0.0.1.dev1
Summary: 
